setup.py
django_prelaunch.egg-info/PKG-INFO
django_prelaunch.egg-info/SOURCES.txt
django_prelaunch.egg-info/dependency_links.txt
django_prelaunch.egg-info/top_level.txt
prelaunch/__init__.py
prelaunch/admin.py
prelaunch/forms.py
prelaunch/middleware.py
prelaunch/models.py
prelaunch/settings.py
prelaunch/shorten.py
prelaunch/templatetags/__init__.py
prelaunch/templatetags/prelaunch_tags.py