Metadata-Version: 1.0
Name: django-prelaunch
Version: 0.1
Summary: A Django app to gather email addresses of people interested in your prelaunch-stage website.
Home-page: http://github.com/jbeyers/django-prelaunch
Author: Johan Beyers
Author-email: jbeyers@juizi.com
License: BSD
Keywords: django
Platform: UNKNOWN
Classifier: Programming Language :: Python
Classifier: Topic :: Software Development :: Libraries :: Python Modules
Classifier: Framework :: Django
Classifier: Intended Audience :: Developers
Classifier: Environment :: Web Environment
Classifier: Development Status :: 4 - Beta
